litsearch_linux/__init__.py
litsearch_linux/search_buddy_linux.py
search_buddy_linux/__init__.py
search_buddy_linux/command_line.py
search_buddy_linux/search_buddy_linux.py
search_buddy_linux-1.0.3.dist-info/LICENSE.txt
search_buddy_linux-1.0.3.dist-info/METADATA
search_buddy_linux-1.0.3.dist-info/WHEEL
search_buddy_linux-1.0.3.dist-info/entry_points.txt
search_buddy_linux-1.0.3.dist-info/top_level.txt
search_buddy_linux-1.0.3.dist-info/RECORD
