Metadata-Version: 2.1
Name: search-buddy-linux
Version: 1.0.3
Summary: A tool to simplify initial literature searches
Home-page: https://github.com/soapGame34/lib-search-buddy-linux
Author: Alexander J. Calder
Author-email: alexcalder91@gmail.com
License: MIT
Keywords: research literature-search
Platform: UNKNOWN
Classifier: Development Status :: 4 - Beta
Classifier: Intended Audience :: Science/Research
Classifier: Topic :: Terminals
Classifier: License :: OSI Approved :: MIT License
Classifier: Programming Language :: Python
License-File: LICENSE.txt
Requires-Dist: selenium
Requires-Dist: webdriver-manager
Requires-Dist: pandas
